portablemc/__init__.py
portablemc/__main__.py
portablemc/auth.py
portablemc/cli/__init__.py
portablemc/cli/complete.py
portablemc/cli/lang.py
portablemc/cli/output.py
portablemc/cli/parse.py
portablemc/cli/util.py
portablemc/download.py
portablemc/fabric.py
portablemc/forge.py
portablemc/http.py
portablemc/standard.py
portablemc/util.py
portablemc-4.3.0.dist-info/entry_points.txt
portablemc-4.3.0.dist-info/LICENSE
portablemc-4.3.0.dist-info/METADATA
portablemc-4.3.0.dist-info/WHEEL
portablemc-4.3.0.dist-info/RECORD
