Metadata-Version: 2.1
Name: portablemc
Version: 4.3.0
Summary: PortableMC is a module that provides both an API for development of your custom launcher and an executable script to run PortableMC CLI.
Home-page: https://github.com/mindstorm38/portablemc
License: GPL-3.0-only
Keywords: minecraft,launcher,portable,cli
Author: Théo Rozier
Author-email: contact@theorozier.fr
Requires-Python: >=3.8
Classifier: Development Status :: 5 - Production/Stable
Classifier: Environment :: Console
Classifier: License :: OSI Approved :: GNU General Public License v3 (GPLv3)
Classifier: Programming Language :: Python :: 3
Classifier: Programming Language :: Python :: 3.8
Classifier: Programming Language :: Python :: 3.9
Classifier: Programming Language :: Python :: 3.10
Classifier: Programming Language :: Python :: 3.11
Classifier: Programming Language :: Python :: 3.12
Provides-Extra: certifi
Requires-Dist: certifi ; extra == "certifi"
Project-URL: Documentation, https://github.com/mindstorm38/portablemc
Project-URL: Repository, https://github.com/mindstorm38/portablemc
